test/__init__.py
test/generatorTest.py
test/loaderTest.py
test/samplingTest.py
tool/__init__.py
tool/config/__init__.py
tool/config/generator.py
tool/database/__init__.py
tool/database/devutils.py
tool/database/query.py
tool/database/queryInterface.py
tool/database/setup.py
tool/loader/__init__.py
tool/loader/formatter.py
tool/loader/loader.py
tool/loader/validator.py
tool/utils/__init__.py
tool/utils/distribute.py
tool/utils/fuzzysearch.py
tool/utils/sampling.py
STITCHED-0.1.0.dist-info/METADATA
STITCHED-0.1.0.dist-info/WHEEL
STITCHED-0.1.0.dist-info/top_level.txt
STITCHED-0.1.0.dist-info/RECORD
