Metadata-Version: 2.1
Name: STITCHED
Version: 0.1.0
Home-page: https://github.com/Master-Project-Hate-Speech/Data-Pipeline
Author: UZH STITCHED
Author-email: 
License: Apache License 2.0
Project-URL: Source, https://github.com/Master-Project-Hate-Speech/Data-Pipeline
Keywords: NLP hate speech pipeline
Classifier: Programming Language :: Python :: 3
Classifier: License :: OSI Approved :: Apache Software License
Classifier: Operating System :: OS Independent
Requires-Python: >=3.6
